[{"id":"1101172001","district_id":"110117","name":"Buket Gadeng","postal_code":"23778"},{"id":"1101172002","district_id":"110117","name":"Rambong","postal_code":"23778"},{"id":"1101172003","district_id":"110117","name":"Seuneubok Keuranji","postal_code":"23778"},{"id":"1101172004","district_id":"110117","name":"Seuneubok Alur Buloh","postal_code":"23778"},{"id":"1101172005","district_id":"110117","name":"Ujong Tanoh","postal_code":"23778"},{"id":"1101172006","district_id":"110117","name":"Ujong Gunong Cut","postal_code":"23778"},{"id":"1101172007","district_id":"110117","name":"Ujong Gunung Rayeuk","postal_code":"23778"},{"id":"1101172008","district_id":"110117","name":"Beutong","postal_code":"23778"},{"id":"1101172009","district_id":"110117","name":"Jambo Keupok","postal_code":"23778"},{"id":"1101172010","district_id":"110117","name":"Alurduamas","postal_code":"23778"}]