[{"id":"1102062001","district_id":"110206","name":"Pardomuan II","postal_code":"24673"},{"id":"1102062002","district_id":"110206","name":"Lawe Desky I","postal_code":"24673"},{"id":"1102062003","district_id":"110206","name":"Lawe Desky Sabas","postal_code":"24673"},{"id":"1102062004","district_id":"110206","name":"Pardomuan I","postal_code":"24673"},{"id":"1102062005","district_id":"110206","name":"Cinta Damai","postal_code":"24673"},{"id":"1102062006","district_id":"110206","name":"Lawe Perbunga","postal_code":"24673"},{"id":"1102062007","district_id":"110206","name":"Lawe Desky Tongah","postal_code":"24673"},{"id":"1102062008","district_id":"110206","name":"Kute Bakti","postal_code":"24673"},{"id":"1102062010","district_id":"110206","name":"Muara Situlen","postal_code":"24673"},{"id":"1102062011","district_id":"110206","name":"Sejahtera","postal_code":"24673"},{"id":"1102062012","district_id":"110206","name":"Kute Makmur","postal_code":"24673"},{"id":"1102062013","district_id":"110206","name":"Pardamean","postal_code":"24673"},{"id":"1102062014","district_id":"110206","name":"Lawe Mantik","postal_code":"24673"},{"id":"1102062015","district_id":"110206","name":"Cinta Makmur","postal_code":"24673"},{"id":"1102062016","district_id":"110206","name":"Muara Setia","postal_code":"24673"},{"id":"1102062017","district_id":"110206","name":"Tanoh Alas","postal_code":"24673"},{"id":"1102062018","district_id":"110206","name":"Sejahtera Baru","postal_code":"24673"},{"id":"1102062024","district_id":"110206","name":"Lawe Tawakh","postal_code":"24673"},{"id":"1102062025","district_id":"110206","name":"Sabilussalam","postal_code":"24673"},{"id":"1102062026","district_id":"110206","name":"Lawe Desky Jaya","postal_code":"24673"},{"id":"1102062027","district_id":"110206","name":"Pintu Alas","postal_code":"24673"}]