[{"id":"1372021001","district_id":"137202","name":"Koto Panjang","postal_code":"27323"},{"id":"1372021002","district_id":"137202","name":"Pasar Pandan Air Mati","postal_code":"27322"},{"id":"1372021003","district_id":"137202","name":"Tanjung Paku","postal_code":"27324"},{"id":"1372021004","district_id":"137202","name":"Nan Balimo","postal_code":"27326"},{"id":"1372021005","district_id":"137202","name":"Kampung Jawa","postal_code":"27321"},{"id":"1372021006","district_id":"137202","name":"Laing","postal_code":"27325"}]