[{"id":"1407101001","district_id":"140710","name":"Bangko Kanan","postal_code":"28993"},{"id":"1407101006","district_id":"140710","name":"Bangko Kiri","postal_code":"28993"},{"id":"1407102002","district_id":"140710","name":"Bangko Jaya","postal_code":"28993"},{"id":"1407102003","district_id":"140710","name":"Bangko Sempurna","postal_code":"28993"},{"id":"1407102004","district_id":"140710","name":"Bangko Bakti","postal_code":"28993"},{"id":"1407102005","district_id":"140710","name":"Bangko Pusako","postal_code":"28993"},{"id":"1407102007","district_id":"140710","name":"Sei Manasib","postal_code":"28993"},{"id":"1407102008","district_id":"140710","name":"Teluk Bano I","postal_code":"28993"},{"id":"1407102009","district_id":"140710","name":"Bangko Makmur","postal_code":"28993"},{"id":"1407102010","district_id":"140710","name":"Pematang Damar","postal_code":"28993"},{"id":"1407102011","district_id":"140710","name":"Pematang Ibul","postal_code":"28993"},{"id":"1407102012","district_id":"140710","name":"Bangko Permata","postal_code":"28993"},{"id":"1407102013","district_id":"140710","name":"Bangko Mukti","postal_code":"28993"},{"id":"1407102014","district_id":"140710","name":"Bangko Lestari","postal_code":"28993"},{"id":"1407102015","district_id":"140710","name":"Bangko Balam","postal_code":"28993"},{"id":"1407102016","district_id":"140710","name":"Bangko Mas Raya","postal_code":"28993"}]