[{"id":"1601092001","district_id":"160109","name":"Kepayang","postal_code":"32191"},{"id":"1601092002","district_id":"160109","name":"Kedondong","postal_code":"32191"},{"id":"1601092003","district_id":"160109","name":"Belimbing","postal_code":"32191"},{"id":"1601092004","district_id":"160109","name":"Durian","postal_code":"32191"},{"id":"1601092006","district_id":"160109","name":"Lubuk Rukam","postal_code":"32191"},{"id":"1601092007","district_id":"160109","name":"Bindu","postal_code":"32191"},{"id":"1601092009","district_id":"160109","name":"Mendala","postal_code":"32191"},{"id":"1601092010","district_id":"160109","name":"Peninjauan","postal_code":"32191"},{"id":"1601092011","district_id":"160109","name":"Saung Naga","postal_code":"32191"},{"id":"1601092022","district_id":"160109","name":"Makartitama","postal_code":"32191"},{"id":"1601092023","district_id":"160109","name":"Espetiga","postal_code":"32191"},{"id":"1601092024","district_id":"160109","name":"Makarti Jaya","postal_code":"32191"},{"id":"1601092025","district_id":"160109","name":"Mitra Kencana","postal_code":"32191"},{"id":"1601092026","district_id":"160109","name":"Penilikan","postal_code":"32191"},{"id":"1601092027","district_id":"160109","name":"Panji Jaya","postal_code":"32191"},{"id":"1601092028","district_id":"160109","name":"Karang Dapo","postal_code":"32191"}]