[{"id":"1613041005","district_id":"161304","name":"Bingin Teluk","postal_code":"31655"},{"id":"1613042001","district_id":"161304","name":"Pauh","postal_code":"31655"},{"id":"1613042002","district_id":"161304","name":"Batu Kucing","postal_code":"31655"},{"id":"1613042003","district_id":"161304","name":"Belani","postal_code":"31655"},{"id":"1613042004","district_id":"161304","name":"Tanjung Raja","postal_code":"31655"},{"id":"1613042006","district_id":"161304","name":"Mandi Angin","postal_code":"31655"},{"id":"1613042007","district_id":"161304","name":"Air Bening","postal_code":"31655"},{"id":"1613042008","district_id":"161304","name":"Beringin Sakti","postal_code":"31655"},{"id":"1613042009","district_id":"161304","name":"Beringin Makmur I","postal_code":"31655"},{"id":"1613042010","district_id":"161304","name":"Beringin Makmur II","postal_code":"31655"},{"id":"1613042011","district_id":"161304","name":"Pauh I","postal_code":"31655"},{"id":"1613042012","district_id":"161304","name":"Ketapat Bening","postal_code":"31655"},{"id":"1613042013","district_id":"161304","name":"Mekarsari","postal_code":"31655"}]