[{"id":"3201202001","district_id":"320120","name":"Jagabaya","postal_code":"16360"},{"id":"3201202002","district_id":"320120","name":"Gorowong","postal_code":"16360"},{"id":"3201202003","district_id":"320120","name":"Dago","postal_code":"16360"},{"id":"3201202004","district_id":"320120","name":"Pingku","postal_code":"16360"},{"id":"3201202005","district_id":"320120","name":"Cikuda","postal_code":"16360"},{"id":"3201202006","district_id":"320120","name":"Parungpanjang","postal_code":"16360"},{"id":"3201202007","district_id":"320120","name":"Lumpang","postal_code":"16360"},{"id":"3201202008","district_id":"320120","name":"Cibunar","postal_code":"16360"},{"id":"3201202009","district_id":"320120","name":"Jagabita","postal_code":"16360"},{"id":"3201202010","district_id":"320120","name":"Gintungcilejet","postal_code":"16360"},{"id":"3201202011","district_id":"320120","name":"Kabasiran","postal_code":"16360"}]