[{"id":"3211212001","district_id":"321121","name":"Cikaramas","postal_code":"45352"},{"id":"3211212002","district_id":"321121","name":"Wargaluyu","postal_code":"45352"},{"id":"3211212003","district_id":"321121","name":"Jingkang","postal_code":"45352"},{"id":"3211212004","district_id":"321121","name":"Kamal","postal_code":"45352"},{"id":"3211212005","district_id":"321121","name":"Kertamukti","postal_code":"45352"},{"id":"3211212006","district_id":"321121","name":"Tanjungwangi","postal_code":"45352"},{"id":"3211212007","district_id":"321121","name":"Sukamukti","postal_code":"45352"},{"id":"3211212008","district_id":"321121","name":"Sukatani","postal_code":"45352"},{"id":"3211212009","district_id":"321121","name":"Tanjungmedar","postal_code":"45352"}]