[{"id":"3211052001","district_id":"321105","name":"Cisitu","postal_code":"45363"},{"id":"3211052002","district_id":"321105","name":"Situmekar","postal_code":"45363"},{"id":"3211052003","district_id":"321105","name":"Pajagan","postal_code":"45363"},{"id":"3211052004","district_id":"321105","name":"Cigintung","postal_code":"45363"},{"id":"3211052005","district_id":"321105","name":"Sundamekar","postal_code":"45363"},{"id":"3211052006","district_id":"321105","name":"Linggajaya","postal_code":"45363"},{"id":"3211052007","district_id":"321105","name":"Ranjeng","postal_code":"45363"},{"id":"3211052008","district_id":"321105","name":"Cilopang","postal_code":"45363"},{"id":"3211052009","district_id":"321105","name":"Cimarga","postal_code":"45363"},{"id":"3211052010","district_id":"321105","name":"Cinangsi","postal_code":"45363"}]