[{"id":"3211171001","district_id":"321117","name":"Pasanggrahan Baru","postal_code":"45313"},{"id":"3211171002","district_id":"321117","name":"Kota Kulon","postal_code":"45311"},{"id":"3211171003","district_id":"321117","name":"Regol Wetan","postal_code":"45311"},{"id":"3211171004","district_id":"321117","name":"Cipameungpeuk","postal_code":"45315"},{"id":"3211172005","district_id":"321117","name":"Sukagalih","postal_code":"45311"},{"id":"3211172006","district_id":"321117","name":"Baginda","postal_code":"45311"},{"id":"3211172007","district_id":"321117","name":"Cipancar","postal_code":"45311"},{"id":"3211172008","district_id":"321117","name":"Citengah","postal_code":"45311"},{"id":"3211172009","district_id":"321117","name":"Gunasari","postal_code":"45311"},{"id":"3211172010","district_id":"321117","name":"Sukajaya","postal_code":"45314"},{"id":"3211172011","district_id":"321117","name":"Margamekar","postal_code":"45311"},{"id":"3211172012","district_id":"321117","name":"Ciherang","postal_code":"45311"},{"id":"3211172013","district_id":"321117","name":"Margalaksana","postal_code":"45311"},{"id":"3211172014","district_id":"321117","name":"Mekar Rahayu","postal_code":"45311"}]