[{"id":"3320122001","district_id":"332012","name":"Blimbingrejo","postal_code":"59466"},{"id":"3320122002","district_id":"332012","name":"Tunggulpandean","postal_code":"59466"},{"id":"3320122003","district_id":"332012","name":"Pringtulis","postal_code":"59466"},{"id":"3320122004","district_id":"332012","name":"Jatisari","postal_code":"59466"},{"id":"3320122005","district_id":"332012","name":"Gemiring Kidul","postal_code":"59466"},{"id":"3320122006","district_id":"332012","name":"Gemiring Lor","postal_code":"59466"},{"id":"3320122007","district_id":"332012","name":"Nalumsari","postal_code":"59466"},{"id":"3320122008","district_id":"332012","name":"Tritis","postal_code":"59466"},{"id":"3320122009","district_id":"332012","name":"Daren","postal_code":"59466"},{"id":"3320122010","district_id":"332012","name":"Karangnongko","postal_code":"59466"},{"id":"3320122011","district_id":"332012","name":"Ngetuk","postal_code":"59466"},{"id":"3320122012","district_id":"332012","name":"Bedanpete ","postal_code":"59466"},{"id":"3320122013","district_id":"332012","name":"Muryolobo","postal_code":"59466"},{"id":"3320122014","district_id":"332012","name":"Bategede","postal_code":"59466"},{"id":"3320122015","district_id":"332012","name":"Dorang","postal_code":"59466"}]