[{"id":"3507032001","district_id":"350703","name":"Wonokerto","postal_code":"65179"},{"id":"3507032002","district_id":"350703","name":"Rejosari","postal_code":"65179"},{"id":"3507032003","district_id":"350703","name":"Bantur","postal_code":"65179"},{"id":"3507032004","district_id":"350703","name":"Wonorejo","postal_code":"65179"},{"id":"3507032005","district_id":"350703","name":"Srigonco","postal_code":"65179"},{"id":"3507032006","district_id":"350703","name":"Sumberbening","postal_code":"65179"},{"id":"3507032007","district_id":"350703","name":"Bandungrejo","postal_code":"65179"},{"id":"3507032008","district_id":"350703","name":"Pringgondani ","postal_code":"65179"},{"id":"3507032009","district_id":"350703","name":"Rejoyoso","postal_code":"65179"},{"id":"3507032010","district_id":"350703","name":"Karangsari","postal_code":"65179"}]