[{"id":"3603031001","district_id":"360303","name":"Tigaraksa","postal_code":"15721"},{"id":"3603031007","district_id":"360303","name":"Kadu Agung","postal_code":"15721"},{"id":"3603032002","district_id":"360303","name":"Pasir Bolang","postal_code":"15721"},{"id":"3603032003","district_id":"360303","name":"Matagara ","postal_code":"15721"},{"id":"3603032004","district_id":"360303","name":"Pasir Nangka","postal_code":"15721"},{"id":"3603032005","district_id":"360303","name":"Pete","postal_code":"15721"},{"id":"3603032006","district_id":"360303","name":"Tegalsari","postal_code":"15721"},{"id":"3603032008","district_id":"360303","name":"Pematang","postal_code":"15721"},{"id":"3603032009","district_id":"360303","name":"Cisereh","postal_code":"15721"},{"id":"3603032010","district_id":"360303","name":"Margasari ","postal_code":"15721"},{"id":"3603032011","district_id":"360303","name":"Cileles","postal_code":"15721"},{"id":"3603032012","district_id":"360303","name":"Sodong","postal_code":"15721"},{"id":"3603032013","district_id":"360303","name":"Tapos","postal_code":"15721"},{"id":"3603032014","district_id":"360303","name":"Bantar Panjang","postal_code":"15721"}]