[{"id":"5103021004","district_id":"510302","name":"Kapal","postal_code":"80351"},{"id":"5103021005","district_id":"510302","name":"Sempidi","postal_code":"80351"},{"id":"5103021014","district_id":"510302","name":"Abianbase","postal_code":"80351"},{"id":"5103021015","district_id":"510302","name":"Sading","postal_code":"80351"},{"id":"5103021016","district_id":"510302","name":"Lukluk","postal_code":"80351"},{"id":"5103022001","district_id":"510302","name":"Munggu","postal_code":"80351"},{"id":"5103022002","district_id":"510302","name":"Buduk","postal_code":"80351"},{"id":"5103022003","district_id":"510302","name":"Mengwitani","postal_code":"80351"},{"id":"5103022006","district_id":"510302","name":"Penarungan","postal_code":"80351"},{"id":"5103022007","district_id":"510302","name":"Sembung","postal_code":"80351"},{"id":"5103022008","district_id":"510302","name":"Baha","postal_code":"80351"},{"id":"5103022009","district_id":"510302","name":"Mengwi","postal_code":"80351"},{"id":"5103022010","district_id":"510302","name":"Kekeran","postal_code":"80351"},{"id":"5103022011","district_id":"510302","name":"Sobangan","postal_code":"80351"},{"id":"5103022012","district_id":"510302","name":"Gulingan","postal_code":"80351"},{"id":"5103022013","district_id":"510302","name":"Werdi Bhuwana","postal_code":"80351"},{"id":"5103022017","district_id":"510302","name":"Cemagi","postal_code":"80351"},{"id":"5103022018","district_id":"510302","name":"Pererenan","postal_code":"80351"},{"id":"5103022019","district_id":"510302","name":"Tumbakbayuh ","postal_code":"80351"},{"id":"5103022020","district_id":"510302","name":"Kuwun ","postal_code":"80351"}]