[{"id":"5105031008","district_id":"510503","name":"Semarapura Kaja","postal_code":"80712"},{"id":"5105031009","district_id":"510503","name":"Semarapura Kauh","postal_code":"80713"},{"id":"5105031010","district_id":"510503","name":"Semarapura Tengah","postal_code":"80711"},{"id":"5105031011","district_id":"510503","name":"Semarapura Kangin","postal_code":"80716"},{"id":"5105031012","district_id":"510503","name":"Semarapura Klod Kangin","postal_code":"80716"},{"id":"5105031013","district_id":"510503","name":"Semarapura Klod","postal_code":"80716"},{"id":"5105032001","district_id":"510503","name":"Satra","postal_code":"80716"},{"id":"5105032002","district_id":"510503","name":"Tojan","postal_code":"80716"},{"id":"5105032003","district_id":"510503","name":"Gelgel","postal_code":"80716"},{"id":"5105032004","district_id":"510503","name":"Kampung Gelgel","postal_code":"80716"},{"id":"5105032005","district_id":"510503","name":"Jumpai","postal_code":"80716"},{"id":"5105032006","district_id":"510503","name":"Tangkas","postal_code":"80716"},{"id":"5105032007","district_id":"510503","name":"Kamasan","postal_code":"80716"},{"id":"5105032014","district_id":"510503","name":"Akah","postal_code":"80716"},{"id":"5105032015","district_id":"510503","name":"Manduang","postal_code":"80716"},{"id":"5105032016","district_id":"510503","name":"Selat","postal_code":"80716"},{"id":"5105032017","district_id":"510503","name":"Tegak","postal_code":"80716"},{"id":"5105032018","district_id":"510503","name":"Selisihan","postal_code":"80716"}]