[{"id":"5308022001","district_id":"530802","name":"Aejeti","postal_code":"86362"},{"id":"5308022002","district_id":"530802","name":"Puutara","postal_code":"86362"},{"id":"5308022003","district_id":"530802","name":"Paderape","postal_code":"86362"},{"id":"5308022004","district_id":"530802","name":"Ndoriwoi","postal_code":"86362"},{"id":"5308022005","district_id":"530802","name":"Rorurangga ","postal_code":"86362"},{"id":"5308022006","district_id":"530802","name":"Rendoraterua ","postal_code":"86362"},{"id":"5308022007","district_id":"530802","name":"Redorory ","postal_code":"86362"},{"id":"5308022008","district_id":"530802","name":"Kazo Kapo","postal_code":"86362"},{"id":"5308022009","district_id":"530802","name":"Renga Menge","postal_code":"86362"}]