[{"id":"8106022002","district_id":"810602","name":"Kawa","postal_code":"97562"},{"id":"8106022003","district_id":"810602","name":"Piru","postal_code":"97562"},{"id":"8106022004","district_id":"810602","name":"Neniari \/ Niniari","postal_code":"97562"},{"id":"8106022005","district_id":"810602","name":"Morekau","postal_code":"97562"},{"id":"8106022006","district_id":"810602","name":"Lumoly ","postal_code":"97562"},{"id":"8106022007","district_id":"810602","name":"Eti \/ Ety","postal_code":"97562"},{"id":"8106022008","district_id":"810602","name":"Kaibobo ","postal_code":"97562"}]