[{"id":"9206182001","district_id":"920618","name":"Jahabra","postal_code":"98161"},{"id":"9206182002","district_id":"920618","name":"Ibori","postal_code":"98161"},{"id":"9206182003","district_id":"920618","name":"Menyembru","postal_code":"98161"},{"id":"9206182004","district_id":"920618","name":"Meyorga","postal_code":"98161"},{"id":"9206182005","district_id":"920618","name":"Laudoho","postal_code":"98161"},{"id":"9206182006","district_id":"920618","name":"Eniba","postal_code":"98161"},{"id":"9206182007","district_id":"920618","name":"Mowitka","postal_code":"98161"}]