[{"id":"9406092001","district_id":"940609","name":"Piyakunu","postal_code":"98873"},{"id":"9406092002","district_id":"940609","name":"Diyeugi","postal_code":"98873"},{"id":"9406092003","district_id":"940609","name":"Putaapa","postal_code":"98873"},{"id":"9406092004","district_id":"940609","name":"Atou","postal_code":"98873"},{"id":"9406092005","district_id":"940609","name":"Modio","postal_code":"98873"},{"id":"9406092006","district_id":"940609","name":"Upibega","postal_code":"98873"},{"id":"9406092007","district_id":"940609","name":"Timepa","postal_code":"98873"},{"id":"9406092008","district_id":"940609","name":"Gabaikunu","postal_code":"98873"},{"id":"9406092009","district_id":"940609","name":"Adauwo","postal_code":"98873"},{"id":"9406092010","district_id":"940609","name":"Megaikebo","postal_code":"98873"}]