[{"id":"1101072001","district_id":"110107","name":"Sikulat","postal_code":"23753"},{"id":"1101072002","district_id":"110107","name":"Sawang I","postal_code":"23753"},{"id":"1101072003","district_id":"110107","name":"Meuligo","postal_code":"23753"},{"id":"1101072004","district_id":"110107","name":"Lhok Pawoh","postal_code":"23753"},{"id":"1101072005","district_id":"110107","name":"Sawang II","postal_code":"23753"},{"id":"1101072006","district_id":"110107","name":"Ujung Karang","postal_code":"23753"},{"id":"1101072007","district_id":"110107","name":"Trieng Meuduro Baroh","postal_code":"23753"},{"id":"1101072008","district_id":"110107","name":"Trieng Meuduro Tunong","postal_code":"23753"},{"id":"1101072009","district_id":"110107","name":"Panton Luas","postal_code":"23753"},{"id":"1101072010","district_id":"110107","name":"Simpang Tiga","postal_code":"23753"},{"id":"1101072011","district_id":"110107","name":"Kuta Baro","postal_code":"23753"},{"id":"1101072012","district_id":"110107","name":"Blang Geulinggang ","postal_code":"23753"},{"id":"1101072013","district_id":"110107","name":"Mutiara","postal_code":"23753"},{"id":"1101072014","district_id":"110107","name":"Ujung Padang","postal_code":"23753"},{"id":"1101072015","district_id":"110107","name":"Sawang Ba'u ","postal_code":"23753"}]