[{"id":"1107072001","district_id":"110707","name":"Tampieng Tunong","postal_code":"24171"},{"id":"1107072002","district_id":"110707","name":"Tampieng Baroh","postal_code":"24171"},{"id":"1107072003","district_id":"110707","name":"Dayah Caleue","postal_code":"24171"},{"id":"1107072004","district_id":"110707","name":"Jurong","postal_code":"24171"},{"id":"1107072005","district_id":"110707","name":"Keutapang","postal_code":"24171"},{"id":"1107072006","district_id":"110707","name":"Dayah Keurako","postal_code":"24171"},{"id":"1107072007","district_id":"110707","name":"Mesjid Lam Ujong","postal_code":"24171"},{"id":"1107072008","district_id":"110707","name":"Baro Jruek","postal_code":"24171"},{"id":"1107072009","district_id":"110707","name":"Yub Mee","postal_code":"24171"},{"id":"1107072010","district_id":"110707","name":"Raya Lhok Kaju","postal_code":"24171"},{"id":"1107072011","district_id":"110707","name":"Pulo Gampong U","postal_code":"24171"},{"id":"1107072012","district_id":"110707","name":"Pante Lhok Kaju","postal_code":"24171"},{"id":"1107072014","district_id":"110707","name":"Sukon Tungkop","postal_code":"24171"},{"id":"1107072015","district_id":"110707","name":"Rawa Tungkop","postal_code":"24171"},{"id":"1107072016","district_id":"110707","name":"Mesjid Tungkop","postal_code":"24171"},{"id":"1107072017","district_id":"110707","name":"Dayah Muara Garot","postal_code":"24171"},{"id":"1107072018","district_id":"110707","name":"Pante Garot","postal_code":"24171"},{"id":"1107072019","district_id":"110707","name":"Garot Cut","postal_code":"24171"},{"id":"1107072020","district_id":"110707","name":"Keubang","postal_code":"24171"},{"id":"1107072021","district_id":"110707","name":"Blang Garot","postal_code":"24171"},{"id":"1107072022","district_id":"110707","name":"Meulayu","postal_code":"24171"},{"id":"1107072023","district_id":"110707","name":"Tungkop Cut","postal_code":"24171"},{"id":"1107072024","district_id":"110707","name":"Guci","postal_code":"24171"},{"id":"1107072025","district_id":"110707","name":"Teungoh Blang","postal_code":"24171"},{"id":"1107072026","district_id":"110707","name":"Mesjid Dijiem","postal_code":"24171"},{"id":"1107072027","district_id":"110707","name":"Sukon Ulee Gampong","postal_code":"24171"},{"id":"1107072028","district_id":"110707","name":"Lamkabu","postal_code":"24171"},{"id":"1107072029","district_id":"110707","name":"Ulee Birah","postal_code":"24171"},{"id":"1107072030","district_id":"110707","name":"Mesjid Baro","postal_code":"24171"},{"id":"1107072031","district_id":"110707","name":"Lamreuneung","postal_code":"24171"},{"id":"1107072032","district_id":"110707","name":"Cot Seukee","postal_code":"24171"},{"id":"1107072033","district_id":"110707","name":"Drien","postal_code":"24171"},{"id":"1107072034","district_id":"110707","name":"Rumia","postal_code":"24171"},{"id":"1107072035","district_id":"110707","name":"Wakheuh","postal_code":"24171"},{"id":"1107072036","district_id":"110707","name":"Baro Bluek","postal_code":"24171"},{"id":"1107072037","district_id":"110707","name":"Mesjid Ulee Gampong","postal_code":"24171"},{"id":"1107072038","district_id":"110707","name":"Dayah Bie","postal_code":"24171"},{"id":"1107072039","district_id":"110707","name":"Balee Baroh Bluek","postal_code":"24171"},{"id":"1107072040","district_id":"110707","name":"Peutoe","postal_code":"24171"},{"id":"1107072041","district_id":"110707","name":"Blang Rapai","postal_code":"24171"},{"id":"1107072042","district_id":"110707","name":"Neulop II","postal_code":"24171"},{"id":"1107072043","district_id":"110707","name":"Baro Gapui","postal_code":"24171"},{"id":"1107072044","district_id":"110707","name":"Balee Baroh Gapui","postal_code":"24171"},{"id":"1107072045","district_id":"110707","name":"Glee Gapui","postal_code":"24171"},{"id":"1107072046","district_id":"110707","name":"Teungoh Suwiek","postal_code":"24171"},{"id":"1107072047","district_id":"110707","name":"Mesjid Suwiek","postal_code":"24171"},{"id":"1107072048","district_id":"110707","name":"Tuha Suwiek","postal_code":"24171"},{"id":"1107072049","district_id":"110707","name":"Beureudep","postal_code":"24171"},{"id":"1107072050","district_id":"110707","name":"Blang Lhok Kaju","postal_code":"24171"}]