[{"id":"1174032001","district_id":"117403","name":"Teungoh ","postal_code":"24416"},{"id":"1174032002","district_id":"117403","name":"Peukan Langsa","postal_code":"24412"},{"id":"1174032004","district_id":"117403","name":"Jawa ","postal_code":"24416"},{"id":"1174032005","district_id":"117403","name":"Paya Bujok Blang Pase","postal_code":"24414"},{"id":"1174032006","district_id":"117403","name":"Blang ","postal_code":"24416"},{"id":"1174032007","district_id":"117403","name":"Alue Beurawe ","postal_code":"24410"},{"id":"1174032009","district_id":"117403","name":"Daulat ","postal_code":"24416"},{"id":"1174032010","district_id":"117403","name":"Meutia ","postal_code":"24416"},{"id":"1174032011","district_id":"117403","name":"Blang Sinibong\/Seunibong","postal_code":"24412"},{"id":"1174032013","district_id":"117403","name":"Tualang Teungoh","postal_code":"24414"}]