[{"id":"1705132001","district_id":"170513","name":"Pagar","postal_code":"38886"},{"id":"1705132002","district_id":"170513","name":"Muara Simpur","postal_code":"38886"},{"id":"1705132003","district_id":"170513","name":"Pagar Agung","postal_code":"38886"},{"id":"1705132004","district_id":"170513","name":"Pagar Banyu","postal_code":"38886"},{"id":"1705132005","district_id":"170513","name":"Simpur Ijang","postal_code":"38886"},{"id":"1705132006","district_id":"170513","name":"Air Keruh","postal_code":"38886"},{"id":"1705132007","district_id":"170513","name":"Hargo Binangun","postal_code":"38886"},{"id":"1705132008","district_id":"170513","name":"Mekar Jaya","postal_code":"38886"},{"id":"1705132009","district_id":"170513","name":"Giri Nanto","postal_code":"38886"},{"id":"1705132010","district_id":"170513","name":"Banyu Kencana","postal_code":"38886"},{"id":"1705132011","district_id":"170513","name":"Muara Nibung","postal_code":"38886"},{"id":"1705132012","district_id":"170513","name":"Tanjung Agung","postal_code":"38886"},{"id":"1705132013","district_id":"170513","name":"Giri Mulya","postal_code":"38886"}]