[{"id":"3175071001","district_id":"317507","name":"Duren Sawit","postal_code":"13440"},{"id":"3175071002","district_id":"317507","name":"Pondok Bambu","postal_code":"13430"},{"id":"3175071003","district_id":"317507","name":"Klender","postal_code":"13470"},{"id":"3175071004","district_id":"317507","name":"Pondok Kelapa","postal_code":"13450"},{"id":"3175071005","district_id":"317507","name":"Malaka Sari","postal_code":"13460"},{"id":"3175071006","district_id":"317507","name":"Malaka Jaya","postal_code":"13460"},{"id":"3175071007","district_id":"317507","name":"Pondok Kopi","postal_code":"13460"}]