[{"id":"3203152001","district_id":"320315","name":"Cidadap","postal_code":"43263"},{"id":"3203152002","district_id":"320315","name":"Cimenteng","postal_code":"43263"},{"id":"3203152003","district_id":"320315","name":"Susukan","postal_code":"43263"},{"id":"3203152004","district_id":"320315","name":"Sukajadi","postal_code":"43263"},{"id":"3203152005","district_id":"320315","name":"Sukadana","postal_code":"43263"},{"id":"3203152006","district_id":"320315","name":"Margaluyu","postal_code":"43263"},{"id":"3203152007","district_id":"320315","name":"Karyamukti","postal_code":"43263"},{"id":"3203152008","district_id":"320315","name":"Campaka","postal_code":"43263"},{"id":"3203152009","district_id":"320315","name":"Wangunjaya","postal_code":"43263"},{"id":"3203152010","district_id":"320315","name":"Girimukti","postal_code":"43263"},{"id":"3203152011","district_id":"320315","name":"Mekarjaya","postal_code":"43263"}]