[{"id":"3213112002","district_id":"321311","name":"Rancasari","postal_code":"41264"},{"id":"3213112003","district_id":"321311","name":"Rancahilir","postal_code":"41264"},{"id":"3213112004","district_id":"321311","name":"Pamanukan","postal_code":"41264"},{"id":"3213112006","district_id":"321311","name":"Pamanukan Hilir","postal_code":"41264"},{"id":"3213112007","district_id":"321311","name":"Pamanukan Sebrang","postal_code":"41264"},{"id":"3213112009","district_id":"321311","name":"Mulyasari","postal_code":"41264"},{"id":"3213112010","district_id":"321311","name":"Lengkongjaya","postal_code":"41264"},{"id":"3213112011","district_id":"321311","name":"Bongas","postal_code":"41264"}]