[{"id":"3518182001","district_id":"351818","name":"Sugihwaras","postal_code":"64452"},{"id":"3518182002","district_id":"351818","name":"Ngluyu","postal_code":"64452"},{"id":"3518182003","district_id":"351818","name":"Tempuran","postal_code":"64452"},{"id":"3518182004","district_id":"351818","name":"Lengkong Lor","postal_code":"64452"},{"id":"3518182005","district_id":"351818","name":"Gampeng","postal_code":"64452"},{"id":"3518182006","district_id":"351818","name":"Bajang","postal_code":"64452"}]