[{"id":"5317012001","district_id":"531701","name":"Makata Keri","postal_code":"87282"},{"id":"5317012003","district_id":"531701","name":"Kabela Wuntu","postal_code":"87282"},{"id":"5317012004","district_id":"531701","name":"Mata Woga","postal_code":"87282"},{"id":"5317012019","district_id":"531701","name":"Umbu Riri","postal_code":"87282"},{"id":"5317012023","district_id":"531701","name":"Anakalang","postal_code":"87282"},{"id":"5317012024","district_id":"531701","name":"Dewa Jara","postal_code":"87282"},{"id":"5317012025","district_id":"531701","name":"Mata Redi","postal_code":"87282"}]