[{"id":"6302202001","district_id":"630220","name":"Tanjung Lalak Utara","postal_code":"72154"},{"id":"6302202002","district_id":"630220","name":"Tanjung Lalak Selatan","postal_code":"72154"},{"id":"6302202003","district_id":"630220","name":"Pulau Kerayaan","postal_code":"72154"},{"id":"6302202004","district_id":"630220","name":"Kerayaan Utara","postal_code":"72154"},{"id":"6302202005","district_id":"630220","name":"Pulau Kerasian","postal_code":"72154"},{"id":"6302202006","district_id":"630220","name":"Pulau Kerumputan","postal_code":"72154"},{"id":"6302202007","district_id":"630220","name":"Teluk Aru","postal_code":"72154"},{"id":"6302202008","district_id":"630220","name":"Teluk Kemuning","postal_code":"72154"},{"id":"6302202009","district_id":"630220","name":"Oka-Oka","postal_code":"72154"}]