[{"id":"6503032001","district_id":"650303","name":"Tagul","postal_code":"77453"},{"id":"6503032002","district_id":"650303","name":"Lubakan","postal_code":"77453"},{"id":"6503032003","district_id":"650303","name":"Atap","postal_code":"77453"},{"id":"6503032004","district_id":"650303","name":"Manuk Bungkul","postal_code":"77453"},{"id":"6503032005","district_id":"650303","name":"Tujung","postal_code":"77453"},{"id":"6503032006","district_id":"650303","name":"Pagar","postal_code":"77453"},{"id":"6503032007","district_id":"650303","name":"Labuk","postal_code":"77453"},{"id":"6503032008","district_id":"650303","name":"Butas Bagu","postal_code":"77453"},{"id":"6503032009","district_id":"650303","name":"Pelaju","postal_code":"77453"},{"id":"6503032010","district_id":"650303","name":"Tepian","postal_code":"77453"}]