[{"id":"7203081020","district_id":"720308","name":"Ganti","postal_code":"94351"},{"id":"7203081021","district_id":"720308","name":"Kabonga Besar","postal_code":"94351"},{"id":"7203081022","district_id":"720308","name":"Kabonga Kecil","postal_code":"94351"},{"id":"7203081023","district_id":"720308","name":"Gunung Bale","postal_code":"94351"},{"id":"7203081024","district_id":"720308","name":"Maleni","postal_code":"94351"},{"id":"7203081025","district_id":"720308","name":"Tanjung Batu","postal_code":"94351"},{"id":"7203081026","district_id":"720308","name":"Boya","postal_code":"94351"},{"id":"7203081027","district_id":"720308","name":"Labuan Bajo","postal_code":"94351"},{"id":"7203081028","district_id":"720308","name":"Boneoge","postal_code":"94351"},{"id":"7203082012","district_id":"720308","name":"Loli Oge ","postal_code":"94351"},{"id":"7203082013","district_id":"720308","name":"Loli Tasibori ","postal_code":"94351"},{"id":"7203082029","district_id":"720308","name":"Loli Pesua","postal_code":"94351"},{"id":"7203082030","district_id":"720308","name":"Loli Dondo","postal_code":"94351"},{"id":"7203082031","district_id":"720308","name":"Loli Saluran","postal_code":"94351"}]