[{"id":"7309061001","district_id":"730906","name":"Sabila","postal_code":"90563"},{"id":"7309062002","district_id":"730906","name":"Padaelo","postal_code":"90563"},{"id":"7309062003","district_id":"730906","name":"Batu Putih","postal_code":"90563"},{"id":"7309062004","district_id":"730906","name":"Wanua Waru","postal_code":"90563"},{"id":"7309062005","district_id":"730906","name":"Tellupanuae","postal_code":"90563"},{"id":"7309062006","district_id":"730906","name":"Samaenre","postal_code":"90563"},{"id":"7309062007","district_id":"730906","name":"Bentenge","postal_code":"90563"},{"id":"7309062008","district_id":"730906","name":"Matampapole","postal_code":"90563"},{"id":"7309062009","district_id":"730906","name":"Uludaya","postal_code":"90563"},{"id":"7309062010","district_id":"730906","name":"Gatarang Matinggi ","postal_code":"90563"},{"id":"7309062011","district_id":"730906","name":"Barugae","postal_code":"90563"}]