[{"id":"8201082001","district_id":"820108","name":"Tosoa","postal_code":"97756"},{"id":"8201082002","district_id":"820108","name":"Tobobol","postal_code":"97756"},{"id":"8201082003","district_id":"820108","name":"Baru","postal_code":"97756"},{"id":"8201082004","district_id":"820108","name":"Nanas","postal_code":"97756"},{"id":"8201082005","district_id":"820108","name":"Jere","postal_code":"97756"},{"id":"8201082006","district_id":"820108","name":"Gamsungi","postal_code":"97756"},{"id":"8201082007","district_id":"820108","name":"Bataka","postal_code":"97756"},{"id":"8201082008","district_id":"820108","name":"Talaga","postal_code":"97756"},{"id":"8201082009","district_id":"820108","name":"Tobelos","postal_code":"97756"},{"id":"8201082010","district_id":"820108","name":"Gamkonora","postal_code":"97756"},{"id":"8201082011","district_id":"820108","name":"Sarau","postal_code":"97756"},{"id":"8201082012","district_id":"820108","name":"Ngawet","postal_code":"97756"},{"id":"8201082013","district_id":"820108","name":"Adu","postal_code":"97756"},{"id":"8201082014","district_id":"820108","name":"Gamsida","postal_code":"97756"},{"id":"8201082015","district_id":"820108","name":"Ngalo Ngalo","postal_code":"97756"},{"id":"8201082016","district_id":"820108","name":"Tuguaer","postal_code":"97756"}]