[{"id":"9120022001","district_id":"912002","name":"Dabra","postal_code":"98694"},{"id":"9120022002","district_id":"912002","name":"Taiyeve","postal_code":"98694"},{"id":"9120022003","district_id":"912002","name":"Fuao","postal_code":"98694"},{"id":"9120022004","district_id":"912002","name":"Papasena I","postal_code":"98694"},{"id":"9120022005","district_id":"912002","name":"Papasena II","postal_code":"98694"},{"id":"9120022006","district_id":"912002","name":"Dou","postal_code":"98694"},{"id":"9120022008","district_id":"912002","name":"Fokri","postal_code":"98694"},{"id":"9120022015","district_id":"912002","name":"Taria","postal_code":"98695"}]