[{"id":"9211042001","district_id":"921104","name":"Isim","postal_code":"98326"},{"id":"9211042002","district_id":"921104","name":"Duhugesa","postal_code":"98326"},{"id":"9211042003","district_id":"921104","name":"Tubes","postal_code":"98326"},{"id":"9211042004","district_id":"921104","name":"Umohousi","postal_code":"98326"},{"id":"9211042005","district_id":"921104","name":"Tohosta","postal_code":"98326"},{"id":"9211042006","district_id":"921104","name":"Hugomot","postal_code":"98326"},{"id":"9211042007","district_id":"921104","name":"Dihisu","postal_code":"98326"},{"id":"9211042008","district_id":"921104","name":"Inyuara","postal_code":"98326"},{"id":"9211042009","district_id":"921104","name":"Desra","postal_code":"98326"},{"id":"9211042010","district_id":"921104","name":"Mindermes","postal_code":"98326"},{"id":"9211042011","district_id":"921104","name":"Sibjo","postal_code":"98326"},{"id":"9211042012","district_id":"921104","name":"Dibera","postal_code":"98326"}]