[{"id":"9504402001","district_id":"950440","name":"Peyola","postal_code":"99016"},{"id":"9504402002","district_id":"950440","name":"Kogotime","postal_code":"99016"},{"id":"9504402003","district_id":"950440","name":"Gabunam","postal_code":"99016"},{"id":"9504402004","district_id":"950440","name":"Gulak","postal_code":"99016"},{"id":"9504402005","district_id":"950440","name":"Melaga","postal_code":"99016"},{"id":"9504402006","district_id":"950440","name":"Ekoni","postal_code":"99016"},{"id":"9504402007","district_id":"950440","name":"Minggen","postal_code":"99016"},{"id":"9504402008","district_id":"950440","name":"Kandimbaga","postal_code":"99016"},{"id":"9504402009","district_id":"950440","name":"Kinebe","postal_code":"99016"},{"id":"9504402010","district_id":"950440","name":"Belela","postal_code":"99016"}]